{
  "garages": [
    {
      "id": "lit-simmons-bank-arena",
      "name": "Simmons Bank Arena (N. Little Rock)",
      "addr": "1 Simmons Bank Arena Way, N Little Rock",
      "lat": 34.7607,
      "lng": -92.2669,
      "height_in": null,
      "height_label": "No limit (uncovered)",
      "oversized": false,
      "notes": "Concert arena across Arkansas River. Surface lots.",
      "source": "simmonsbankarena.com"
    },
    {
      "id": "lit-dickey-stephens",
      "name": "Dickey-Stephens Park (Travelers)",
      "addr": "400 W Broadway St, N Little Rock",
      "lat": 34.7549,
      "lng": -92.2803,
      "height_in": null,
      "height_label": null,
      "oversized": false,
      "notes": "AA Arkansas Travelers.",
      "source": "milb.com",
      "entrance_lat": 34.7556654,
      "entrance_lng": -92.2803134,
      "entrance_source": "Auto (nearest Street View pano within 300m, 2026-04-24)"
    },
    {
      "id": "lit-statehouse-conv-ctr",
      "name": "Statehouse Convention Center Garage",
      "addr": "7 Statehouse Plaza",
      "lat": 34.745,
      "lng": -92.2719,
      "height_in": null,
      "height_label": null,
      "oversized": false,
      "notes": "Downtown convention.",
      "source": "littlerockmeetings.com"
    },
    {
      "id": "lit-river-market",
      "name": "River Market District Lots",
      "addr": "400 President Clinton Ave",
      "lat": 34.7475,
      "lng": -92.266,
      "height_in": null,
      "height_label": "No limit (uncovered)",
      "oversized": false,
      "notes": "Farmers + food hall district.",
      "source": "rivermarket.info"
    },
    {
      "id": "lit-clinton-library",
      "name": "William J. Clinton Presidential Library",
      "addr": "1200 President Clinton Ave",
      "lat": 34.7455,
      "lng": -92.2585,
      "height_in": null,
      "height_label": "No limit (uncovered)",
      "oversized": true,
      "notes": "Library + museum surface lot.",
      "source": "clintonlibrary.gov"
    },
    {
      "id": "lit-arkansas-state-capitol",
      "name": "Arkansas State Capitol Grounds",
      "addr": "500 Woodlane St",
      "lat": 34.7466,
      "lng": -92.2884,
      "height_in": null,
      "height_label": "No limit (uncovered)",
      "oversized": false,
      "notes": "Capitol Square.",
      "source": "sos.arkansas.gov",
      "entrance_lat": 34.7459759,
      "entrance_lng": -92.2866618,
      "entrance_source": "OSM parking_entrance node 5263886041"
    },
    {
      "id": "lit-old-statehouse",
      "name": "Old State House Museum Lot",
      "addr": "300 W Markham St",
      "lat": 34.7473,
      "lng": -92.2731,
      "height_in": null,
      "height_label": "No limit (uncovered)",
      "oversized": false,
      "notes": "Historic 1836 statehouse.",
      "source": "oldstatehouse.com"
    },
    {
      "id": "lit-mcarthur-park",
      "name": "MacArthur Park / MacArthur Museum",
      "addr": "503 E 9th St",
      "lat": 34.739,
      "lng": -92.2689,
      "height_in": null,
      "height_label": "No limit (uncovered)",
      "oversized": false,
      "notes": "Downtown park.",
      "source": "littlerock.gov"
    },
    {
      "id": "lit-arkansas-art-ctr",
      "name": "Arkansas Museum of Fine Arts (AMFA)",
      "addr": "501 E 9th St",
      "lat": 34.7386,
      "lng": -92.2691,
      "height_in": null,
      "height_label": null,
      "oversized": false,
      "notes": "Recently rebuilt 2023. Underground garage.",
      "source": "arkmfa.org"
    },
    {
      "id": "lit-heifer-international",
      "name": "Heifer International World Avenue",
      "addr": "1 World Ave",
      "lat": 34.7479,
      "lng": -92.259,
      "height_in": null,
      "height_label": "No limit (uncovered)",
      "oversized": false,
      "notes": "HQ + museum.",
      "source": "heifer.org"
    },
    {
      "id": "lit-arkansas-inn-library",
      "name": "Main Library / Central Arkansas Library",
      "addr": "100 Rock St",
      "lat": 34.7481,
      "lng": -92.2674,
      "height_in": null,
      "height_label": null,
      "oversized": false,
      "notes": "Free library garage.",
      "source": "cals.org"
    },
    {
      "id": "lit-war-memorial-stadium",
      "name": "War Memorial Stadium",
      "addr": "1 Stadium Dr",
      "lat": 34.7492,
      "lng": -92.3155,
      "height_in": null,
      "height_label": "No limit (uncovered)",
      "oversized": true,
      "notes": "Arkansas football (occasional). Surface lots.",
      "source": "armemorialstadium.org"
    },
    {
      "id": "lit-ar-state-fairgrounds",
      "name": "Arkansas State Fairgrounds",
      "addr": "2600 Howard St",
      "lat": 34.7245,
      "lng": -92.2944,
      "height_in": null,
      "height_label": "No limit (uncovered)",
      "oversized": true,
      "notes": "State fair venue.",
      "source": "arkansasstatefair.com"
    },
    {
      "id": "lit-zoo",
      "name": "Little Rock Zoo",
      "addr": "1 Zoo Dr",
      "lat": 34.7489,
      "lng": -92.3111,
      "height_in": null,
      "height_label": "No limit (uncovered)",
      "oversized": true,
      "notes": "Surface lot.",
      "source": "littlerockzoo.com"
    },
    {
      "id": "lit-park-plaza-mall",
      "name": "Park Plaza Mall",
      "addr": "6000 W Markham St",
      "lat": 34.7502,
      "lng": -92.3411,
      "height_in": null,
      "height_label": null,
      "oversized": false,
      "notes": "Enclosed mall.",
      "source": "shopparkplaza.com",
      "entrance_lat": 34.7510588,
      "entrance_lng": -92.3424434,
      "entrance_source": "OSM parking_entrance node 4058987526"
    },
    {
      "id": "lit-summit-mall",
      "name": "The Outlets of Little Rock",
      "addr": "11201 Bass Pro Pkwy",
      "lat": 34.8072,
      "lng": -92.4158,
      "height_in": null,
      "height_label": "No limit (uncovered)",
      "oversized": false,
      "notes": "Outlet center.",
      "source": "Needs verification",
      "entrance_lat": 34.8045272,
      "entrance_lng": -92.4165351,
      "entrance_source": "Auto (nearest Street View pano within 300m, 2026-04-24)"
    },
    {
      "id": "lit-hillcrest",
      "name": "Hillcrest District Lots",
      "addr": "2710 Kavanaugh Blvd",
      "lat": 34.7614,
      "lng": -92.2996,
      "height_in": null,
      "height_label": "No limit (uncovered)",
      "oversized": false,
      "notes": "Historic shopping district.",
      "source": "Needs verification"
    },
    {
      "id": "lit-south-main",
      "name": "SoMa (South Main Street) District",
      "addr": "1312 S Main St",
      "lat": 34.7366,
      "lng": -92.2734,
      "height_in": null,
      "height_label": "No limit (uncovered)",
      "oversized": false,
      "notes": "Arts district.",
      "source": "Needs verification"
    },
    {
      "id": "lit-argenta-district",
      "name": "Argenta District (N. Little Rock)",
      "addr": "400 Main St, N Little Rock",
      "lat": 34.7549,
      "lng": -92.2734,
      "height_in": null,
      "height_label": "No limit (uncovered)",
      "oversized": false,
      "notes": "Arts + dining district.",
      "source": "argentaartsdistrict.com"
    },
    {
      "id": "lit-lit-airport-garage",
      "name": "Little Rock Clinton Airport (LIT) Garage",
      "addr": "1 Airport Rd",
      "lat": 34.7295,
      "lng": -92.2239,
      "height_in": null,
      "height_label": null,
      "oversized": false,
      "notes": "Terminal-adjacent.",
      "source": "clintonairport.com"
    },
    {
      "id": "lit-lit-airport-economy",
      "name": "LIT \u2014 Economy Lot",
      "addr": "1 Airport Rd",
      "lat": 34.7283,
      "lng": -92.2272,
      "height_in": null,
      "height_label": "No limit (uncovered)",
      "oversized": true,
      "notes": "Uncovered.",
      "source": "clintonairport.com",
      "entrance_lat": 34.7278079,
      "entrance_lng": -92.2239278,
      "entrance_source": "Auto (nearest Street View pano within 300m, 2026-04-24)"
    },
    {
      "id": "osm-n13358264883",
      "name": "RV Park (unnamed)",
      "addr": "",
      "lat": 34.82471,
      "lng": -92.15781,
      "height_in": null,
      "height_label": "No limit (uncovered)",
      "oversized": true,
      "structure_type": "surface_lot",
      "notes": "Imported 2026 from OSM as an oversized-vehicle-friendly surface lot: RV park (OSM tourism=caravan_site).",
      "source": "OpenStreetMap (surface lot)"
    },
    {
      "id": "osm-w223009356",
      "name": "Love's",
      "addr": "",
      "lat": 34.65685,
      "lng": -92.41355,
      "height_in": null,
      "height_label": "No limit (uncovered)",
      "oversized": true,
      "structure_type": "surface_lot",
      "notes": "Imported 2026 from OSM as an oversized-vehicle-friendly surface lot: HGV-friendly (OSM hgv=yes). Paid parking. Operator: Love's.",
      "source": "OpenStreetMap (surface lot)"
    },
    {
      "id": "osm-w585196281",
      "name": "Kroger",
      "addr": "",
      "lat": 34.80404,
      "lng": -92.42995,
      "height_in": null,
      "height_label": "No limit (uncovered)",
      "oversized": true,
      "structure_type": "surface_lot",
      "notes": "Imported 2026 from OSM as an oversized-vehicle-friendly surface lot: large capacity (500 spaces). 500 spaces. Operator: Kroger.",
      "source": "OpenStreetMap (surface lot)"
    },
    {
      "id": "osm-w622351934",
      "name": "Downtown Riverside RV Park",
      "addr": "250 South Locust Street",
      "lat": 34.75168,
      "lng": -92.25997,
      "height_in": null,
      "height_label": "No limit (uncovered)",
      "oversized": true,
      "structure_type": "surface_lot",
      "notes": "Imported 2026 from OSM as an oversized-vehicle-friendly surface lot: RV park (OSM tourism=caravan_site). 61 spaces. Operator: City of North Little Rock.",
      "source": "OpenStreetMap (surface lot)"
    },
    {
      "id": "osm-w668478236",
      "name": "Burns Park - RV Campground",
      "addr": "4101 Arlene Layman Drive",
      "lat": 34.79774,
      "lng": -92.31411,
      "height_in": null,
      "height_label": "No limit (uncovered)",
      "oversized": true,
      "structure_type": "surface_lot",
      "notes": "Imported 2026 from OSM as an oversized-vehicle-friendly surface lot: RV park (OSM tourism=caravan_site). 54 spaces.",
      "source": "OpenStreetMap (surface lot)"
    },
    {
      "id": "osm-w1196820748",
      "name": "RV Park (unnamed)",
      "addr": "",
      "lat": 34.81479,
      "lng": -92.34907,
      "height_in": null,
      "height_label": "No limit (uncovered)",
      "oversized": true,
      "structure_type": "surface_lot",
      "notes": "Imported 2026 from OSM as an oversized-vehicle-friendly surface lot: RV park (OSM tourism=caravan_site).",
      "source": "OpenStreetMap (surface lot)",
      "entrance_lat": 34.8139687,
      "entrance_lng": -92.348838,
      "entrance_source": "Auto (nearest Street View pano within 300m, 2026-04-24 surface-lot pass)"
    }
  ],
  "tunnels": [],
  "bridges": [
    {
      "id": "lit-big-dam-bridge",
      "name": "Big Dam Bridge (pedestrian)",
      "addr": "over Arkansas River near Murray Lock",
      "lat": 34.7867,
      "lng": -92.3599,
      "height_in": null,
      "height_label": "Pedestrian only",
      "notes": "Longest pedestrian bridge in US built specifically for walkers.",
      "source": "bigdambridge.com"
    },
    {
      "id": "lit-main-st-bridge",
      "name": "Main Street Bridge",
      "addr": "Main St over Arkansas River",
      "lat": 34.7512,
      "lng": -92.2715,
      "height_in": null,
      "height_label": "Over water",
      "notes": "Downtown connector to N Little Rock.",
      "source": "Wikipedia",
      "entrance_lat": 34.7493757,
      "entrance_lng": -92.2720136,
      "entrance_source": "Auto (nearest Street View pano within 300m, 2026-04-24)"
    },
    {
      "id": "lit-broadway-bridge",
      "name": "Broadway Bridge",
      "addr": "Broadway over Arkansas River",
      "lat": 34.7509,
      "lng": -92.2759,
      "height_in": null,
      "height_label": "Over water",
      "notes": "Replaced 2017.",
      "source": "ardot.gov"
    },
    {
      "id": "lit-i30-bridge",
      "name": "I-30 Arkansas River Bridge",
      "addr": "I-30 over Arkansas River",
      "lat": 34.7454,
      "lng": -92.2642,
      "height_in": null,
      "height_label": "Over water",
      "notes": "Major interstate crossing.",
      "source": "ardot.gov"
    },
    {
      "id": "nbi-05-000000000019624",
      "name": "Low on-bridge clearance: Park Drive",
      "addr": "Park Drive",
      "lat": 34.80409,
      "lng": -92.32622,
      "height_in": 141,
      "height_label": "11'9\"",
      "notes": "FHWA NBI; on-bridge clearance; built 1972",
      "source": "FHWA National Bridge Inventory"
    },
    {
      "id": "nbi-05-0000000000A5316",
      "name": "Low on-bridge clearance: I 430 NB Log 7.32",
      "addr": "I 430 NB Log 7.32",
      "lat": 34.76326,
      "lng": -92.39063,
      "height_in": 176,
      "height_label": "14'8\"",
      "notes": "FHWA NBI; on-bridge clearance; built 1972",
      "source": "FHWA National Bridge Inventory"
    }
  ]
}
