{
  "garages": [
    {
      "id": "orl-disney-magic-kingdom",
      "name": "Walt Disney World \u2014 Magic Kingdom TTC",
      "addr": "3111 World Dr",
      "lat": 28.4151,
      "lng": -81.5836,
      "height_in": null,
      "height_label": "No limit (uncovered)",
      "oversized": true,
      "notes": "Transportation + Ticket Center. Massive lot. RV/oversized OK.",
      "source": "disneyworld.disney.go.com"
    },
    {
      "id": "orl-disney-epcot",
      "name": "Walt Disney World \u2014 EPCOT Lot",
      "addr": "200 EPCOT Center Dr",
      "lat": 28.3747,
      "lng": -81.5494,
      "height_in": null,
      "height_label": "No limit (uncovered)",
      "oversized": true,
      "notes": "EPCOT parking lot.",
      "source": "disneyworld.disney.go.com"
    },
    {
      "id": "orl-disney-hollywood-studios",
      "name": "WDW \u2014 Hollywood Studios Lot",
      "addr": "351 S Studio Dr",
      "lat": 28.3585,
      "lng": -81.5584,
      "height_in": null,
      "height_label": "No limit (uncovered)",
      "oversized": true,
      "notes": "DHS surface lot.",
      "source": "disneyworld.disney.go.com"
    },
    {
      "id": "orl-disney-animal-kingdom",
      "name": "WDW \u2014 Animal Kingdom Lot",
      "addr": "2901 Osceola Pkwy",
      "lat": 28.3562,
      "lng": -81.5905,
      "height_in": null,
      "height_label": "No limit (uncovered)",
      "oversized": true,
      "notes": "Animal Kingdom.",
      "source": "disneyworld.disney.go.com"
    },
    {
      "id": "orl-disney-springs",
      "name": "Disney Springs \u2014 Orange + Lime Garages",
      "addr": "1486 Buena Vista Dr",
      "lat": 28.3698,
      "lng": -81.5178,
      "height_in": null,
      "height_label": null,
      "oversized": false,
      "notes": "Disney Springs shopping/dining garages. Free.",
      "source": "disneysprings.com"
    },
    {
      "id": "orl-universal-garages",
      "name": "Universal Orlando \u2014 Parking Garages",
      "addr": "6000 Universal Blvd",
      "lat": 28.4756,
      "lng": -81.4659,
      "height_in": null,
      "height_label": null,
      "oversized": false,
      "notes": "Universal Studios + Islands of Adventure garages.",
      "source": "universalorlando.com"
    },
    {
      "id": "orl-universal-prime",
      "name": "Universal \u2014 Prime Self-Parking",
      "addr": "6000 Universal Blvd",
      "lat": 28.4751,
      "lng": -81.464,
      "height_in": null,
      "height_label": null,
      "oversized": false,
      "notes": "Upper-tier closer garages.",
      "source": "universalorlando.com"
    },
    {
      "id": "orl-seaworld",
      "name": "SeaWorld Orlando",
      "addr": "7007 Sea World Dr",
      "lat": 28.4103,
      "lng": -81.4615,
      "height_in": null,
      "height_label": "No limit (uncovered)",
      "oversized": true,
      "notes": "Theme park surface lot. Oversized OK.",
      "source": "seaworld.com"
    },
    {
      "id": "orl-oc-convention-ctr",
      "name": "Orange County Convention Center \u2014 West Lots",
      "addr": "9800 International Dr",
      "lat": 28.4242,
      "lng": -81.4698,
      "height_in": null,
      "height_label": null,
      "oversized": false,
      "notes": "OCCC West garage.",
      "source": "occc.net"
    },
    {
      "id": "orl-occc-north-south",
      "name": "OCCC \u2014 North/South Garage",
      "addr": "9400 Universal Blvd",
      "lat": 28.4285,
      "lng": -81.4672,
      "height_in": null,
      "height_label": null,
      "oversized": false,
      "notes": "North/South building garage.",
      "source": "occc.net"
    },
    {
      "id": "orl-intl-drive",
      "name": "International Drive \u2014 Pointe Orlando",
      "addr": "9101 International Dr",
      "lat": 28.4308,
      "lng": -81.466,
      "height_in": null,
      "height_label": null,
      "oversized": false,
      "notes": "I-Drive entertainment complex.",
      "source": "pointeorlando.com"
    },
    {
      "id": "orl-icon-park",
      "name": "ICON Park (I-Drive 360)",
      "addr": "8375 International Dr",
      "lat": 28.4427,
      "lng": -81.4696,
      "height_in": null,
      "height_label": null,
      "oversized": false,
      "notes": "Observation wheel + aquarium.",
      "source": "iconparkorlando.com"
    },
    {
      "id": "orl-downtown-church-st",
      "name": "Church Street Garage",
      "addr": "55 W Church St",
      "lat": 28.54,
      "lng": -81.3818,
      "height_in": null,
      "height_label": null,
      "oversized": false,
      "notes": "Downtown Orlando.",
      "source": "cityoforlando.net"
    },
    {
      "id": "orl-kia-ctr",
      "name": "Kia Center (Magic) Garage",
      "addr": "400 W Church St",
      "lat": 28.539,
      "lng": -81.3836,
      "height_in": null,
      "height_label": null,
      "oversized": false,
      "notes": "Orlando Magic arena.",
      "source": "kiacenter.com"
    },
    {
      "id": "orl-dr-phillips-center",
      "name": "Dr. Phillips Center for Performing Arts",
      "addr": "445 S Magnolia Ave",
      "lat": 28.5389,
      "lng": -81.3769,
      "height_in": null,
      "height_label": null,
      "oversized": false,
      "notes": "Broadway tours + symphony.",
      "source": "drphillipscenter.org"
    },
    {
      "id": "orl-inter-miami-orl-city",
      "name": "Inter&Co Stadium (Orlando City SC)",
      "addr": "655 W Church St",
      "lat": 28.5411,
      "lng": -81.3901,
      "height_in": null,
      "height_label": "No limit (uncovered)",
      "oversized": false,
      "notes": "MLS stadium lots.",
      "source": "orlandocitysc.com"
    },
    {
      "id": "orl-camping-world-stadium",
      "name": "Camping World Stadium \u2014 Citrus Bowl Lots",
      "addr": "One Citrus Bowl Pl",
      "lat": 28.5389,
      "lng": -81.4026,
      "height_in": null,
      "height_label": "No limit (uncovered)",
      "oversized": true,
      "notes": "Citrus Bowl + concerts. Surface lots.",
      "source": "campingworldstadium.com"
    },
    {
      "id": "orl-millenia-mall",
      "name": "The Mall at Millenia",
      "addr": "4200 Conroy Rd",
      "lat": 28.4855,
      "lng": -81.4279,
      "height_in": null,
      "height_label": null,
      "oversized": false,
      "notes": "Upscale mall garage.",
      "source": "mallatmillenia.com"
    },
    {
      "id": "orl-florida-mall",
      "name": "Florida Mall",
      "addr": "8001 S Orange Blossom Trl",
      "lat": 28.4471,
      "lng": -81.3987,
      "height_in": null,
      "height_label": "No limit (uncovered)",
      "oversized": false,
      "notes": "Major enclosed mall.",
      "source": "simon.com"
    },
    {
      "id": "orl-premium-outlets-vineland",
      "name": "Orlando Vineland Premium Outlets",
      "addr": "8200 Vineland Ave",
      "lat": 28.4062,
      "lng": -81.4764,
      "height_in": null,
      "height_label": "No limit (uncovered)",
      "oversized": false,
      "notes": "Outlet mall surface.",
      "source": "premiumoutlets.com"
    },
    {
      "id": "orl-premium-outlets-intl",
      "name": "Orlando International Premium Outlets",
      "addr": "4951 International Dr",
      "lat": 28.4788,
      "lng": -81.4635,
      "height_in": null,
      "height_label": "No limit (uncovered)",
      "oversized": false,
      "notes": "Outlet mall.",
      "source": "premiumoutlets.com"
    },
    {
      "id": "orl-orlando-health",
      "name": "Orlando Health (ORMC) Visitor Garage",
      "addr": "1414 Kuhl Ave",
      "lat": 28.5296,
      "lng": -81.3771,
      "height_in": null,
      "height_label": null,
      "oversized": false,
      "notes": "Hospital visitor garage.",
      "source": "orlandohealth.com"
    },
    {
      "id": "orl-mco-terminal-a",
      "name": "MCO Airport \u2014 Terminal A Garage",
      "addr": "1 Jeff Fuqua Blvd",
      "lat": 28.4302,
      "lng": -81.3067,
      "height_in": null,
      "height_label": null,
      "oversized": false,
      "notes": "Terminal A.",
      "source": "orlandoairports.net"
    },
    {
      "id": "orl-mco-terminal-b",
      "name": "MCO \u2014 Terminal B Garage",
      "addr": "1 Jeff Fuqua Blvd",
      "lat": 28.4292,
      "lng": -81.3085,
      "height_in": null,
      "height_label": null,
      "oversized": false,
      "notes": "Terminal B.",
      "source": "orlandoairports.net"
    },
    {
      "id": "orl-mco-terminal-c",
      "name": "MCO \u2014 Terminal C Garage (new)",
      "addr": "1 Jeff Fuqua Blvd",
      "lat": 28.4233,
      "lng": -81.3,
      "height_in": null,
      "height_label": null,
      "oversized": false,
      "notes": "New 2022 South Terminal garage.",
      "source": "orlandoairports.net"
    },
    {
      "id": "orl-mco-economy",
      "name": "MCO \u2014 Park Economy Lot",
      "addr": "1 Jeff Fuqua Blvd",
      "lat": 28.422,
      "lng": -81.316,
      "height_in": null,
      "height_label": "No limit (uncovered)",
      "oversized": true,
      "notes": "Uncovered.",
      "source": "orlandoairports.net"
    },
    {
      "id": "orl-fort-wilderness",
      "name": "Disney Fort Wilderness Resort & Campground",
      "addr": "3520 N Fort Wilderness Trl",
      "lat": 28.4127,
      "lng": -81.563,
      "height_in": null,
      "height_label": "No limit (uncovered)",
      "oversized": true,
      "notes": "On-Disney RV campground.",
      "source": "disneyworld.disney.go.com"
    }
  ],
  "tunnels": [],
  "bridges": [
    {
      "id": "orl-i4-ultimate",
      "name": "I-4 Ultimate \u2014 Downtown Flyovers",
      "addr": "I-4 through downtown",
      "lat": 28.54,
      "lng": -81.386,
      "height_in": 168,
      "height_label": "14'0\"",
      "notes": "Rebuilt interstate. Standard clearance.",
      "source": "FDOT"
    },
    {
      "id": "nbi-12-755825",
      "name": "Low on-bridge clearance: Entrance CNL park",
      "addr": "Entrance CNL park",
      "lat": 28.5367,
      "lng": -81.38065,
      "height_in": 81,
      "height_label": "6'9\"",
      "notes": "FHWA NBI; on-bridge clearance; built 2009",
      "source": "FHWA National Bridge Inventory"
    },
    {
      "id": "nbi-12-755826",
      "name": "Low clearance: Drainage Canal under Tavistock Lakes Bl",
      "addr": "Drainage Canal",
      "lat": 28.37241,
      "lng": -81.24679,
      "height_in": 114,
      "height_label": "9'6\"",
      "notes": "FHWA NBI; under-bridge clearance; built 2011; bridge carries Tavistock Lakes Bl",
      "source": "FHWA National Bridge Inventory"
    },
    {
      "id": "nbi-12-755906",
      "name": "Low on-bridge clearance: Jeff Fuqua Blvd.",
      "addr": "Jeff Fuqua Blvd.",
      "lat": 28.43197,
      "lng": -81.31134,
      "height_in": 175,
      "height_label": "14'7\"",
      "notes": "FHWA NBI; on-bridge clearance; built 1981",
      "source": "FHWA National Bridge Inventory"
    },
    {
      "id": "nbi-12-755907",
      "name": "Low on-bridge clearance: Jeff Fuqua Blvd.",
      "addr": "Jeff Fuqua Blvd.",
      "lat": 28.4303,
      "lng": -81.31134,
      "height_in": 173,
      "height_label": "14'5\"",
      "notes": "FHWA NBI; on-bridge clearance; built 1981",
      "source": "FHWA National Bridge Inventory"
    },
    {
      "id": "nbi-12-755908",
      "name": "Low on-bridge clearance: 2nd Level Deplan A",
      "addr": "2nd Level Deplan A",
      "lat": 28.43218,
      "lng": -81.31031,
      "height_in": 172,
      "height_label": "14'4\"",
      "notes": "FHWA NBI; on-bridge clearance; built 1981",
      "source": "FHWA National Bridge Inventory"
    },
    {
      "id": "nbi-12-755909",
      "name": "Low on-bridge clearance: 2nd Level Deplan B",
      "addr": "2nd Level Deplan B",
      "lat": 28.43,
      "lng": -81.30774,
      "height_in": 173,
      "height_label": "14'5\"",
      "notes": "FHWA NBI; on-bridge clearance; built 1981",
      "source": "FHWA National Bridge Inventory"
    }
  ]
}
